pixelflux/__init__.py
pixelflux/pixelflux_wayland.cpython-312-x86_64-linux-musl.so
pixelflux/screen_capture_module.so
pixelflux.libs/libSPIRV-Tools-0811532b.so
pixelflux.libs/libSPIRV-Tools-opt-f58f01f2.so
pixelflux.libs/libSvtAv1Enc-b4dffd6c.so.2.3.0
pixelflux.libs/libaom-f3f706e2.so.3.12.1
pixelflux.libs/libass-9a00e928.so.9.3.1
pixelflux.libs/libavcodec-0c3d1ccf.so.60.31.102
pixelflux.libs/libavfilter-367a8298.so.9.12.100
pixelflux.libs/libavformat-648ac4e7.so.60.16.100
pixelflux.libs/libavutil-897a956e.so.58.29.100
pixelflux.libs/libbluray-10ef2f2e.so.2.4.3
pixelflux.libs/libbrotlicommon-5bc645f4.so.1.1.0
pixelflux.libs/libbrotlidec-310e5392.so.1.1.0
pixelflux.libs/libbrotlienc-9dc02fdf.so.1.1.0
pixelflux.libs/libbz2-b428631a.so.1.0.8
pixelflux.libs/libcjson-3756410f.so.1.7.19
pixelflux.libs/libcrypto-524aa652.so.3
pixelflux.libs/libdav1d-c9cf1086.so.7.0.0
pixelflux.libs/libdovi-867af97d.so.3.3.1
pixelflux.libs/libexpat-e4f7ec7e.so.1.11.1
pixelflux.libs/libfontconfig-448d4009.so.1.12.1
pixelflux.libs/libfreetype-3e8802a2.so.6.20.2
pixelflux.libs/libfribidi-2518c67d.so.0.4.0
pixelflux.libs/libglslang-394c81bb.so.15.2.0
pixelflux.libs/libglslang-default-resource-limits-24bc816e.so.15.2.0
pixelflux.libs/libgomp-8949ffbe.so.1.0.0
pixelflux.libs/libgraphite2-8ec8d6d4.so.3.2.1
pixelflux.libs/libharfbuzz-38ed6ee8.so.0.61121.0
pixelflux.libs/libhwy-af778bc4.so.1.0.7
pixelflux.libs/libjpeg-e06775bb.so.8.3.2
pixelflux.libs/libjxl-7af5f5c5.so.0.10.3
pixelflux.libs/libjxl_cms-9b2cd007.so.0.10.3
pixelflux.libs/libjxl_threads-0cebd00b.so.0.10.3
pixelflux.libs/liblcms2-2ce9bc4a.so.2.0.16
pixelflux.libs/liblilv-0-e16876d7.so.0.24.26
pixelflux.libs/libmbedcrypto-227b4f9d.so.3.6.5
pixelflux.libs/libmp3lame-2b22ab5b.so.0.0.0
pixelflux.libs/libmpg123-b41dc201.so.0.48.3
pixelflux.libs/libnuma-0126b216.so.1.0.0
pixelflux.libs/libogg-61fdb6da.so.0.8.5
pixelflux.libs/libopenmpt-580caf09.so.0.4.4
pixelflux.libs/libopus-42fc9042.so.0.10.1
pixelflux-1.5.9.dist-info/METADATA
pixelflux-1.5.9.dist-info/WHEEL
pixelflux-1.5.9.dist-info/top_level.txt
pixelflux-1.5.9.dist-info/RECORD
pixelflux-1.5.9.dist-info/licenses/LICENSE
pixelflux-1.5.9.dist-info/sboms/auditwheel.cdx.json
