Metadata-Version: 2.4
Name: pixelflux
Version: 1.5.9
Summary: A performant web native pixel delivery pipeline for diverse sources, blending VNC-inspired parallel processing of pixel buffers with flexible modern encoding formats.
Home-page: https://github.com/linuxserver/pixelflux
Author: Linuxserver.io
Author-email: pypi@linuxserver.io
License: MPL-2.0
Classifier: Programming Language :: Python :: 3
Classifier: Operating System :: POSIX :: Linux
Requires-Python: >=3.6
License-File: LICENSE
Dynamic: author
Dynamic: author-email
Dynamic: classifier
Dynamic: description
Dynamic: description-content-type
Dynamic: home-page
Dynamic: license
Dynamic: license-file
Dynamic: requires-python
Dynamic: summary
